AUTHORS.rst
CONTRIBUTING.rst
HISTORY.rst
MANIFEST.in
README.md
setup.cfg
setup.py
docs/Makefile
docs/authors.rst
docs/conf.py
docs/contributing.rst
docs/history.rst
docs/index.rst
docs/installation.rst
docs/make.bat
docs/readme.rst
docs/usage.rst
mltrics/__init__.py
mltrics/cli.py
mltrics/mltrics.py
mltrics/models.py
mltrics.egg-info/PKG-INFO
mltrics.egg-info/SOURCES.txt
mltrics.egg-info/dependency_links.txt
mltrics.egg-info/entry_points.txt
mltrics.egg-info/not-zip-safe
mltrics.egg-info/requires.txt
mltrics.egg-info/top_level.txt
tests/__init__.py
tests/test_mltrics.py