Metadata-Version: 2.1
Name: mltrics
Version: 0.1.4
Summary: Monitor ML models in production
Home-page: https://mltrics.ai
Author: Mltrics team
Author-email: hello@mltrics.ai
License: UNKNOWN
Keywords: mltrics
Platform: UNKNOWN
Classifier: Development Status :: 2 - Pre-Alpha
Classifier: Intended Audience :: Developers
Classifier: Natural Language :: English
Classifier: Programming Language :: Python :: 3
Classifier: Programming Language :: Python :: 3.6
Classifier: Programming Language :: Python :: 3.7
Classifier: Programming Language :: Python :: 3.8
Requires-Python: >=3.6
